[
	{
		"name": "Syrup Castle 37",
		"access_rules": ["syrupcastle"],
		"sections": [
			{
				"ref": "Syrup Castle 37 - Normal Exit/Normal Exit"
			},
			{
				"ref": "Syrup Castle 37 - Treasure N/Treasure N"
			},
			{
				"ref": "Syrup Castle 37 - Block 1/Block 1",
			},
			{
				"ref": "Syrup Castle 37 - Block 2/Block 2",
			},
			{
				"ref": "Syrup Castle 37 - Block 3/Block 3",
			},
			{
				"ref": "Syrup Castle 37 - Block 4/Block 4",
			},
			{
				"ref": "Syrup Castle 37 - Block 5/Block 5",
			},
			{
				"ref": "Syrup Castle 37 - Block 6/Block 6",
			},
			{
				"ref": "Syrup Castle 37 - Block 7/Block 7",
			},
			{
				"ref": "Syrup Castle 37 - Block 8/Block 8",
			},
			{
				"ref": "Syrup Castle 37 - Block 9/Block 9",
			},
			{
				"ref": "Syrup Castle 37 - Block 10/Block 10",
			},
			{
				"ref": "Syrup Castle 37 - Block 11/Block 11",
			},
			{
				"ref": "Syrup Castle 37 - Block 12/Block 12",
			},
			{
				"ref": "Syrup Castle 37 - Block 13/Block 13",
			},
			{
				"ref": "Syrup Castle 37 - Block 14/Block 14",
			},
			{
				"ref": "Syrup Castle 37 - Block 15/Block 15",
			},
			{
				"ref": "Syrup Castle 37 - Block 16/Block 16",
			},
			{
				"ref": "Syrup Castle 37 - Block 17/Block 17",
			},
			{
				"ref": "Syrup Castle 37 - Block 18/Block 18",
			},
			{
				"ref": "Syrup Castle 37 - Block 19/Block 19",
			},
			{
				"ref": "Syrup Castle 37 - Block 20/Block 20",
			},
			{
				"ref": "Syrup Castle 37 - Block 21/Block 21",
			},			
		],
		"map_locations": [
			{
				"map": "Syrup Castle",
				"x": 99,
				"y": 124
			}
		]
	}
]